speckitadv-3.2.0.dist-info/WHEEL
speckitadv-3.2.0.dist-info/entry_points.txt
speckitadv-3.2.0.dist-info/top_level.txt
speckitadv-3.2.0.dist-info/METADATA
speckitadv-3.2.0.dist-info/RECORD
speckitadv-3.2.0.dist-info/licenses/LICENSE
speckit/__main__.cpython-313-x86_64-linux-gnu.so
speckit/cli.cpython-313-x86_64-linux-gnu.so
speckit/__init__.py
speckit/commands/constitution.cpython-313-x86_64-linux-gnu.so
speckit/commands/guidelines.cpython-313-x86_64-linux-gnu.so
speckit/commands/workflow.cpython-313-x86_64-linux-gnu.so
speckit/commands/analyze_project.cpython-313-x86_64-linux-gnu.so
speckit/commands/project.cpython-313-x86_64-linux-gnu.so
speckit/commands/__init__.py
speckit/commands/feature.cpython-313-x86_64-linux-gnu.so
speckit/setup/init_cmd.cpython-313-x86_64-linux-gnu.so
speckit/setup/config.cpython-313-x86_64-linux-gnu.so
speckit/setup/check_cmd.cpython-313-x86_64-linux-gnu.so
speckit/setup/__init__.py
speckit/assets/config-template.json
speckit/assets/AGENTS.md
speckit/assets/__init__.py
speckit/assets/prompts/resume.md
speckit/assets/prompts/orchestrate.md
speckit/assets/prompts/__init__.py
speckit/assets/prompts/deepwiki/14-examples.md
speckit/assets/prompts/deepwiki/03-quickstart.md
speckit/assets/prompts/deepwiki/10-config.md
speckit/assets/prompts/deepwiki/13-errors.md
speckit/assets/prompts/deepwiki/02-business-context.md
speckit/assets/prompts/deepwiki/07-components.md
speckit/assets/prompts/deepwiki/08-api.md
speckit/assets/prompts/deepwiki/06-flows.md
speckit/assets/prompts/deepwiki/05-diagrams.md
speckit/assets/prompts/deepwiki/11-dependencies.md
speckit/assets/prompts/deepwiki/04-overview.md
speckit/assets/prompts/deepwiki/09-models.md
speckit/assets/prompts/deepwiki/12-decisions.md
speckit/assets/prompts/deepwiki/01-check-repoix.md
speckit/assets/prompts/deepwiki/15-enrichment.md
speckit/assets/prompts/deepwiki/16-summary.md
speckit/assets/prompts/analyze/01-setup.md
speckit/assets/prompts/analyze/03-report.md
speckit/assets/prompts/analyze/02-detection.md
speckit/assets/prompts/plan/02-setup.md
speckit/assets/prompts/plan/03-research.md
speckit/assets/prompts/plan/04-design.md
speckit/assets/prompts/plan/01-initialization.md
