Metadata-Version: 2.4
Name: speckitadv
Version: 3.2.0
Summary: Spec Kit Advanced - Zero-Prompt Architecture CLI for AI-powered development
Author: Civyk
License: Proprietary
Project-URL: Homepage, https://github.com/veerabhadra-ponna/spec-kit-adv
Project-URL: Repository, https://github.com/veerabhadra-ponna/spec-kit-adv
Project-URL: Issues, https://github.com/veerabhadra-ponna/spec-kit-adv/issues
Keywords: ai,cli,development,specification,code-generation
Classifier: Development Status :: 4 - Beta
Classifier: Environment :: Console
Classifier: Intended Audience :: Developers
Classifier: License :: Other/Proprietary License
Classifier: Operating System :: OS Independent
Classifier: Programming Language :: Python :: 3
Classifier: Programming Language :: Python :: 3.10
Classifier: Programming Language :: Python :: 3.11
Classifier: Programming Language :: Python :: 3.12
Classifier: Programming Language :: Python :: 3.13
Classifier: Programming Language :: C
Classifier: Topic :: Software Development
Classifier: Topic :: Software Development :: Code Generators
Requires-Python: >=3.10
License-File: LICENSE
Requires-Dist: typer>=0.9.0
Requires-Dist: rich>=13.0.0
Requires-Dist: pydantic>=2.0.0
Provides-Extra: dev
Requires-Dist: pytest>=7.0.0; extra == "dev"
Requires-Dist: pytest-cov>=4.0.0; extra == "dev"
Requires-Dist: pytest-xdist>=3.5.0; extra == "dev"
Requires-Dist: pytest-asyncio>=0.23.0; extra == "dev"
Requires-Dist: pyinstaller>=6.0.0; extra == "dev"
Requires-Dist: mypy>=1.0.0; extra == "dev"
Requires-Dist: ruff>=0.1.0; extra == "dev"
Requires-Dist: pyyaml>=6.0.0; extra == "dev"
Requires-Dist: nuitka>=2.0.0; extra == "dev"
Requires-Dist: ordered-set>=4.1.0; extra == "dev"
Dynamic: license-file
